falcon_elastic_apm/__init__.py
falcon_elastic_apm/middleware.py
falcon_elastic_apm/version.py
falcon_elastic_apm-0.1.1.dist-info/LICENSE
falcon_elastic_apm-0.1.1.dist-info/METADATA
falcon_elastic_apm-0.1.1.dist-info/WHEEL
falcon_elastic_apm-0.1.1.dist-info/top_level.txt
falcon_elastic_apm-0.1.1.dist-info/RECORD
